spindle/__init__.py
spindle/data/__init__.py
spindle/data/embedding.py
spindle/models/__init__.py
spindle/models/autoencoder.py
spindle/models/trainer.py
spindle/utils/__init__.py
spindle/utils/analysis.py
spindle/utils/server.py
spindle/utils/weights.py
spindle_ml-0.1.2.dist-info/licenses/LICENSE
spindle_ml-0.1.2.dist-info/METADATA
spindle_ml-0.1.2.dist-info/WHEEL
spindle_ml-0.1.2.dist-info/top_level.txt
spindle_ml-0.1.2.dist-info/RECORD
