Metadata-Version: 2.4
Name: spindle-ml
Version: 0.1.2
Summary: A library for training and deploying Sparse Autoencoders
Home-page: https://github.com/wafer-inc/spindle
Author: Sam Hall
Author-email: sam@wafer.systems
Classifier: Programming Language :: Python :: 3
Classifier: License :: OSI Approved :: MIT License
Classifier: Operating System :: OS Independent
Requires-Python: >=3.7
License-File: LICENSE
Requires-Dist: torch>=1.8.0
Requires-Dist: numpy>=1.19.0
Requires-Dist: matplotlib>=3.3.0
Requires-Dist: fastapi>=0.68.0
Requires-Dist: uvicorn>=0.15.0
Requires-Dist: pydantic>=1.8.0
Provides-Extra: transformers
Requires-Dist: transformers>=4.0.0; extra == "transformers"
Requires-Dist: sentence-transformers>=2.0.0; extra == "transformers"
Provides-Extra: server
Requires-Dist: fastapi>=0.68.0; extra == "server"
Requires-Dist: uvicorn>=0.15.0; extra == "server"
Requires-Dist: pydantic>=1.8.0; extra == "server"
Dynamic: author
Dynamic: author-email
Dynamic: classifier
Dynamic: description
Dynamic: description-content-type
Dynamic: home-page
Dynamic: license-file
Dynamic: provides-extra
Dynamic: requires-dist
Dynamic: requires-python
Dynamic: summary
